odoo8_addon_account_banking_payment_export-8.0.0.3.0.99.dev51-py3.8-nspkg.pth
odoo_addons/account_banking_payment_export/README.rst
odoo_addons/account_banking_payment_export/__init__.py
odoo_addons/account_banking_payment_export/__openerp__.py
odoo_addons/account_banking_payment_export/data/bank_payment_line_seq.xml
odoo_addons/account_banking_payment_export/data/payment_mode_type.xml
odoo_addons/account_banking_payment_export/demo/banking_demo.xml
odoo_addons/account_banking_payment_export/i18n/account_banking_payment_export.pot
odoo_addons/account_banking_payment_export/i18n/am.po
odoo_addons/account_banking_payment_export/i18n/ar.po
odoo_addons/account_banking_payment_export/i18n/bg.po
odoo_addons/account_banking_payment_export/i18n/bs.po
odoo_addons/account_banking_payment_export/i18n/ca.po
odoo_addons/account_banking_payment_export/i18n/ca_ES.po
odoo_addons/account_banking_payment_export/i18n/cs.po
odoo_addons/account_banking_payment_export/i18n/da.po
odoo_addons/account_banking_payment_export/i18n/de.po
odoo_addons/account_banking_payment_export/i18n/el_GR.po
odoo_addons/account_banking_payment_export/i18n/en_AU.po
odoo_addons/account_banking_payment_export/i18n/en_GB.po
odoo_addons/account_banking_payment_export/i18n/es.po
odoo_addons/account_banking_payment_export/i18n/es_AR.po
odoo_addons/account_banking_payment_export/i18n/es_BO.po
odoo_addons/account_banking_payment_export/i18n/es_CL.po
odoo_addons/account_banking_payment_export/i18n/es_CO.po
odoo_addons/account_banking_payment_export/i18n/es_CR.po
odoo_addons/account_banking_payment_export/i18n/es_DO.po
odoo_addons/account_banking_payment_export/i18n/es_EC.po
odoo_addons/account_banking_payment_export/i18n/es_ES.po
odoo_addons/account_banking_payment_export/i18n/es_MX.po
odoo_addons/account_banking_payment_export/i18n/es_PE.po
odoo_addons/account_banking_payment_export/i18n/es_PY.po
odoo_addons/account_banking_payment_export/i18n/es_VE.po
odoo_addons/account_banking_payment_export/i18n/et.po
odoo8_addon_account_banking_payment_export-8.0.0.3.0.99.dev51.dist-info/METADATA
odoo8_addon_account_banking_payment_export-8.0.0.3.0.99.dev51.dist-info/WHEEL
odoo8_addon_account_banking_payment_export-8.0.0.3.0.99.dev51.dist-info/namespace_packages.txt
odoo8_addon_account_banking_payment_export-8.0.0.3.0.99.dev51.dist-info/top_level.txt
odoo8_addon_account_banking_payment_export-8.0.0.3.0.99.dev51.dist-info/RECORD
