Metadata-Version: 2.1
Name: odoo8-addon-account-banking-payment-export
Version: 8.0.0.3.0.99.dev51
Summary: Account Banking - Payments Export Infrastructure
Home-page: https://github.com/OCA/bank-payment
Author: ACSONE SA/NV, Therp BV, Serv. Tecnol. Avanzados - Pedro M. Baeza, Odoo Community Association (OCA)
Author-email: support@odoo-community.org
License: AGPL-3
Platform: UNKNOWN
Classifier: Programming Language :: Python
Classifier: Framework :: Odoo
Classifier: Framework :: Odoo :: 8.0
Classifier: License :: OSI Approved :: GNU Affero General Public License v3
Requires-Python: ~=2.7
Requires-Dist: odoo (<9.0a,>=8.0a)
